byteparsing/__init__.py
byteparsing/__version__.py
byteparsing/cursor.py
byteparsing/decorator.py
byteparsing/failure.py
byteparsing/openfoam.py
byteparsing/parsers.py
byteparsing/trampoline.py
byteparsing-0.1.2.dist-info/LICENSE
byteparsing-0.1.2.dist-info/WHEEL
byteparsing-0.1.2.dist-info/METADATA
byteparsing-0.1.2.dist-info/RECORD
