Metadata-Version: 2.1
Name: byteparsing
Version: 0.1.2
Summary: Parser for mixed ASCII/binary data formats
Home-page: https://parallelwindfarms.github.io/byteparsing
License: Apache-2.0
Keywords: parsing,binary data
Author: Johan Hidding
Author-email: j.hidding@esciencecenter.nl
Requires-Python: >=3.9,<3.11
Classifier: Development Status :: 2 - Pre-Alpha
Classifier: Intended Audience :: Developers
Classifier: License :: OSI Approved :: Apache Software License
Classifier: Natural Language :: English
Classifier: Programming Language :: Python :: 3
Classifier: Programming Language :: Python :: 3.9
Requires-Dist: numpy (>=1.21.2,<2.0.0)
Project-URL: Repository, https://github.com/parallelwindfarms/byteparsing
